{
  "generator-jhipster": {
    "applicationType": "monolith",
    "authenticationType": "jwt",
    "baseName": "StudentGradingEvalutionSystem",
    "blueprints": [
      {
        "name": "generator-jhipster-nodejs",
        "version": "3.0.0"
      }
    ],
    "clientFramework": "react",
    "clientTestFrameworks": [],
    "clientTheme": "none",
    "creationTimestamp": 1746799764287,
    "devServerPort": 9060,
    "enableTranslation": true,
    "entities": ["User", "Student", "Teacher", "Course", "TeacherCourse", "StudentCourse", "StudentCourseGrade"],
    "jhipsterVersion": "8.5.0",
    "languages": ["en"],
    "lastLiquibaseTimestamp": 1746806440000,
    "microfrontend": null,
    "microfrontends": [],
    "nativeLanguage": "en",
    "prodDatabaseType": "mysql",
    "serverPort": null,
    "testFrameworks": [],
    "withAdminUi": true
  }
}
