{
  "annotations": {
    "changelogDate": "20250509160040"
  },
  "applications": "*",
  "dto": true,
  "fields": [
    {
      "fieldName": "score",
      "fieldType": "Float"
    }
  ],
  "name": "StudentCourseGrade",
  "relationships": [
    {
      "otherEntityName": "student",
      "relationshipName": "student",
      "relationshipSide": "right",
      "relationshipType": "many-to-one"
    },
    {
      "otherEntityName": "course",
      "relationshipName": "course",
      "relationshipSide": "right",
      "relationshipType": "many-to-one"
    }
  ]
}
